watchdog/__init__.py
watchdog/events.py
watchdog/py.typed
watchdog/version.py
watchdog/watchmedo.py
watchdog/observers/__init__.py
watchdog/observers/api.py
watchdog/observers/fsevents.py
watchdog/observers/fsevents2.py
watchdog/observers/inotify.py
watchdog/observers/inotify_buffer.py
watchdog/observers/inotify_c.py
watchdog/observers/kqueue.py
watchdog/observers/polling.py
watchdog/observers/read_directory_changes.py
watchdog/observers/winapi.py
watchdog/tricks/__init__.py
watchdog/utils/__init__.py
watchdog/utils/bricks.py
watchdog/utils/delayed_queue.py
watchdog/utils/dirsnapshot.py
watchdog/utils/echo.py
watchdog/utils/event_debouncer.py
watchdog/utils/patterns.py
watchdog/utils/platform.py
watchdog/utils/process_watcher.py
watchdog-5.0.3.dist-info/AUTHORS
watchdog-5.0.3.dist-info/COPYING
watchdog-5.0.3.dist-info/LICENSE
watchdog-5.0.3.dist-info/METADATA
watchdog-5.0.3.dist-info/WHEEL
watchdog-5.0.3.dist-info/entry_points.txt
watchdog-5.0.3.dist-info/top_level.txt
watchdog-5.0.3.dist-info/RECORD
